django_drupal_auth_backend/__init__.py
django_drupal_auth_backend/hashers.py
django_drupal_auth_backend-1.0.3.dist-info/DESCRIPTION.rst
django_drupal_auth_backend-1.0.3.dist-info/METADATA
django_drupal_auth_backend-1.0.3.dist-info/RECORD
django_drupal_auth_backend-1.0.3.dist-info/WHEEL
django_drupal_auth_backend-1.0.3.dist-info/metadata.json
django_drupal_auth_backend-1.0.3.dist-info/top_level.txt
tests/__init__.py
tests/test_hashers.py
