Metadata-Version: 2.0
Name: django-drupal-auth-backend
Version: 1.0.3
Summary: Authentication backend for Django that works with legacy Drupal 7 accounts.
Home-page: https://github.com/seawolf42/django-drupal-auth-backend
Author: jeffrey k eliasen
Author-email: jeff+django-drupal-auth-backend@jke.net
License: GNU General Public License v3 or later (GPLv3+)
Keywords: django-drupal-auth-backend
Platform: UNKNOWN
Classifier: Environment :: Web Environment
Classifier: Framework :: Django
Classifier: Framework :: Django :: 1.8
Classifier: Framework :: Django :: 1.9
Classifier: Framework :: Django :: 1.10
Classifier: Framework :: Django :: 1.11
Classifier: Framework :: Django :: 2.0
Classifier: Intended Audience :: Developers
Classifier: License :: OSI Approved :: GNU General Public License v3 or later (GPLv3+)
Classifier: Natural Language :: English
Classifier: Operating System :: OS Independent
Classifier: Programming Language :: Python :: 3
Classifier: Programming Language :: Python :: 3.6
Classifier: Topic :: Security
Requires-Dist: Django (>=1.8)
